mino_file_server/__init__.py
mino_file_server-0.2.4.dist-info/METADATA
mino_file_server-0.2.4.dist-info/WHEEL
mino_file_server-0.2.4.dist-info/top_level.txt
mino_file_server-0.2.4.dist-info/RECORD
