Metadata-Version: 2.1
Name: mino_file_server
Version: 0.2.4
Summary: apis for windows file-server
Author-email: byron <1636700244@qq.com>
License: MIT
Requires-Python: ==3.11.*
Requires-Dist: requests>=2.32.3
